{
    "data": {
        "operators": ["Megafon", "MTS", "Biline"],
        "minutes": [
            {
                "value": 200,
                "price": 50
            },
            {
                "value": 250,
                "price": 80
            },
            {
                "value": 600,
                "price": 100
            },
            {
                "value": 650,
                "price": 120
            }
        ],
        "gigabytes": [
            {
                "value": 5,
                "price": 50
            },
            {
                "value": 15,
                "price": 80
            },
            {
                "value": 30,
                "price": 100
            },
            {
                "value": 35,
                "price": 120
            }
        ],
        "router": [
            {
                "name": "wi-fi",
                "value": "rent",
                "signature": "Аренда 99 ₽/мес.",
                "defaultChecked": false,
                "price": 99
            },
            {
                "name": "wi-fi",
                "value": "purchase",
                "signature": "Выкупить 2600",
                "defaultChecked": true,
                "price": 2600
            }
        ],
        "socialNetwork": [
            {
                "name": "facebook",
                "price": "20",
                "icon": "../src/shared/assets/icons/facebook_icon.svg",
                "iconNotChecked": "../src/shared/assets/icons/facebook-not-select-icon.svg"
            },
            {
                "name": "vk",
                "price": "20",
                "icon": "../src/shared/assets/icons/vk_icon.svg",
                "iconNotChecked": "../src/shared/assets/icons/vk-not-select-icon.svg",
                "checked": true
            },
            {
                "name": "odnoklassniki",
                "price": "20",
                "icon": "../src/shared/assets/icons/odnoklass_icon.svg",
                "iconNotChecked": "../src/shared/assets/icons/odnoklassniki-not-select-icon.svg"
            },
            {
                "name": "instagram",
                "price": "20",
                "icon": "../src/shared/assets/icons/inst_icon.svg",
                "iconNotChecked": "../src/shared/assets/icons/instagram-not-select-icon.svg",
                "checked": true
            },
            {
                "name": "tik-tok",
                "price": "20",
                "icon": "../src/shared/assets/icons/tiktok_icon.svg",
                "iconNotChecked": "../src/shared/assets/icons/tiktok-not-select-icon.svg"
            }
        ]
    }
}
